MANIFEST.in
README.txt
setup.cfg
setup.py
vs.flexigridsearch-configure.zcml
docs/HISTORY.txt
docs/INSTALL.txt
docs/LICENSE.GPL
docs/LICENSE.txt
vs/__init__.py
vs.flexigridsearch.egg-info/PKG-INFO
vs.flexigridsearch.egg-info/SOURCES.txt
vs.flexigridsearch.egg-info/dependency_links.txt
vs.flexigridsearch.egg-info/entry_points.txt
vs.flexigridsearch.egg-info/namespace_packages.txt
vs.flexigridsearch.egg-info/not-zip-safe
vs.flexigridsearch.egg-info/paster_plugins.txt
vs.flexigridsearch.egg-info/requires.txt
vs.flexigridsearch.egg-info/top_level.txt
vs/flexigridsearch/__init__.py
vs/flexigridsearch/configure.zcml
vs/flexigridsearch/header.txt
vs/flexigridsearch/profiles.zcml
vs/flexigridsearch/setuphandlers.py
vs/flexigridsearch/skins.zcml
vs/flexigridsearch/version.txt
vs/flexigridsearch/browser/__init__.py
vs/flexigridsearch/browser/configure.zcml
vs/flexigridsearch/browser/search.py
vs/flexigridsearch/locales/README.txt
vs/flexigridsearch/locales/de/LC_MESSAGES/vs.flexigridsearch.po
vs/flexigridsearch/profiles/default/cssregistry.xml
vs/flexigridsearch/profiles/default/jsregistry.xml
vs/flexigridsearch/profiles/default/metadata.xml
vs/flexigridsearch/profiles/default/propertiestool.xml
vs/flexigridsearch/profiles/default/skins.xml
vs/flexigridsearch/profiles/default/viewlets.xml
vs/flexigridsearch/profiles/default/vs.flexigridsearch_various.txt
vs/flexigridsearch/profiles/plone3/cssregistry.xml
vs/flexigridsearch/profiles/plone3/jsregistry.xml
vs/flexigridsearch/profiles/plone3/metadata.xml
vs/flexigridsearch/profiles/plone3/propertiestool.xml
vs/flexigridsearch/profiles/plone3/skins.xml
vs/flexigridsearch/profiles/plone3/viewlets.xml
vs/flexigridsearch/profiles/plone3/vs.flexigridsearch_various.txt
vs/flexigridsearch/skins/vs_flexigridsearch/flexigrid.css
vs/flexigridsearch/skins/vs_flexigridsearch/search.pt
vs/flexigridsearch/skins/vs_flexigridsearch/vs_flexigrid.js
vs/flexigridsearch/skins/vs_flexigridsearch/vs_flexigrid_p4.js
vs/flexigridsearch/skins/vs_flexigridsearch/vs_flexigridsearch_translations.js
vs/flexigridsearch/skins/vs_flexigridsearch/images/bg.gif
vs/flexigridsearch/skins/vs_flexigridsearch/images/btn-sprite.gif
vs/flexigridsearch/skins/vs_flexigridsearch/images/ddn.png
vs/flexigridsearch/skins/vs_flexigridsearch/images/dn.png
vs/flexigridsearch/skins/vs_flexigridsearch/images/fhbg.gif
