Metadata-Version: 1.0
Name: vs.flexigridsearch
Version: 1.0.1
Summary: Plone  search results through flexigrid
Home-page: http://pypi.python.org/pypi/vs.flexigridsearch
Author: Andreas Jung
Author-email: info@zopyx.com
License: GPL
Keywords: Plone jQuery flexigrid Search Zope Search
Platform: UNKNOWN
Classifier: Framework :: Plone
Classifier: Framework :: Plone :: 3.3
Classifier: Framework :: Plone :: 4.0
Classifier: Framework :: Plone :: 4.1
Classifier: Programming Language :: Python
